nilsig/__init__.py
nilsig/key_gen.py
nilsig/nildb_api.py
nilsig/nilql_encryption.py
nilsig/sign.py
nilsig-0.0.0a1.dist-info/LICENSE
nilsig-0.0.0a1.dist-info/METADATA
nilsig-0.0.0a1.dist-info/WHEEL
nilsig-0.0.0a1.dist-info/top_level.txt
nilsig-0.0.0a1.dist-info/RECORD
