Metadata-Version: 2.2
Name: nilsig
Version: 0.0.0a1
Summary: Library for generating signature keys and signing messages using nilVM and nilDB.
Author: Dave Butler
Author-email: david.butler@nillion.com
License: MIT
Project-URL: Repository, https://github.com/nillionnetwork/nilsig-py
Requires-Python: >=3.9
License-File: LICENSE
Requires-Dist: python-dotenv~=1.0.1
Requires-Dist: requests~=2.32
Requires-Dist: cryptography~=3.4
Requires-Dist: nilql==0.0.0a10
Provides-Extra: docs
Requires-Dist: toml~=0.10.2; extra == "docs"
Requires-Dist: sphinx~=5.0; extra == "docs"
Requires-Dist: sphinx-rtd-theme~=2.0.0; extra == "docs"
Provides-Extra: test
Requires-Dist: pytest~=8.2; extra == "test"
Requires-Dist: pytest-cov~=5.0; extra == "test"
Provides-Extra: lint
Requires-Dist: pylint~=3.2.0; extra == "lint"
Provides-Extra: coveralls
Requires-Dist: coveralls~=4.0; extra == "coveralls"
Provides-Extra: publish
Requires-Dist: build~=0.10; extra == "publish"
Requires-Dist: twine~=4.0; extra == "publish"
